dataimport/__init__.py
dataimport/_meta/__init__.py
dataimport/_meta/injector.py
dataimport-0.1.0.dist-info/LICENSE
dataimport-0.1.0.dist-info/METADATA
dataimport-0.1.0.dist-info/WHEEL
dataimport-0.1.0.dist-info/top_level.txt
dataimport-0.1.0.dist-info/RECORD
