Metadata-Version: 2.1
Name: dataimport
Version: 0.1.0
Summary: read datafiles via the import system
Home-page: https://github.com/buckley-w-david/dataimport
Author: David Buckley
Author-email: david@davidbuckley.ca
License: UNKNOWN
Platform: UNKNOWN
